{
    "key": "group_5c923a79e8169",
    "title": "Modules",
    "fields": [
        {
            "key": "field_5c923a83d29a1",
            "label": "Modules",
            "name": "c8_templates",
            "type": "flexible_content",
            "instructions": "",
            "required": 0,
            "conditional_logic": 0,
            "wrapper": {
                "width": "",
                "class": "",
                "id": ""
            },
            "layouts": {
                "layout_61cc0a39fec23": {
                    "key": "layout_61cc0a39fec23",
                    "name": "demo1",
                    "label": "Demo1",
                    "display": "block",
                    "sub_fields": [
                        {
                            "key": "field_63a2913183283",
                            "label": "Alo",
                            "name": "alo",
                            "type": "text",
                            "instructions": "",
                            "required": 0,
                            "conditional_logic": 0,
                            "wrapper": {
                                "width": "",
                                "class": "",
                                "id": ""
                            },
                            "default_value": "",
                            "placeholder": "",
                            "prepend": "",
                            "append": "",
                            "maxlength": ""
                        },
                        {
                            "key": "field_63a2914b83284",
                            "label": "Alo2",
                            "name": "alo2",
                            "type": "text",
                            "instructions": "",
                            "required": 0,
                            "conditional_logic": 0,
                            "wrapper": {
                                "width": "",
                                "class": "",
                                "id": ""
                            },
                            "default_value": "",
                            "placeholder": "",
                            "prepend": "",
                            "append": "",
                            "maxlength": ""
                        }
                    ],
                    "min": "",
                    "max": ""
                },
                "layout_63a27269b7409": {
                    "key": "layout_63a27269b7409",
                    "name": "demo",
                    "label": "Demo",
                    "display": "block",
                    "sub_fields": [
                        {
                            "key": "field_63a272bdb740a",
                            "label": "Title",
                            "name": "title",
                            "type": "text",
                            "instructions": "",
                            "required": 0,
                            "conditional_logic": 0,
                            "wrapper": {
                                "width": "",
                                "class": "",
                                "id": ""
                            },
                            "default_value": "",
                            "placeholder": "",
                            "prepend": "",
                            "append": "",
                            "maxlength": ""
                        },
                        {
                            "key": "field_63a27315b740b",
                            "label": "Desc",
                            "name": "desc",
                            "type": "text",
                            "instructions": "",
                            "required": 0,
                            "conditional_logic": 0,
                            "wrapper": {
                                "width": "",
                                "class": "",
                                "id": ""
                            },
                            "default_value": "",
                            "placeholder": "",
                            "prepend": "",
                            "append": "",
                            "maxlength": ""
                        }
                    ],
                    "min": "",
                    "max": ""
                },
                "layout_6386baab0823a": {
                    "key": "layout_6386baab0823a",
                    "name": "example",
                    "label": "Example",
                    "display": "block",
                    "sub_fields": [],
                    "min": "",
                    "max": ""
                },
                "layout_63934ffbbbec0": {
                    "key": "layout_63934ffbbbec0",
                    "name": "two_column",
                    "label": "Two Column",
                    "display": "block",
                    "sub_fields": [
                        {
                            "key": "field_63945b3e5b339",
                            "label": "Heading",
                            "name": "heading",
                            "type": "text",
                            "instructions": "",
                            "required": 0,
                            "conditional_logic": 0,
                            "wrapper": {
                                "width": "",
                                "class": "",
                                "id": ""
                            },
                            "default_value": "",
                            "placeholder": "",
                            "prepend": "",
                            "append": "",
                            "maxlength": ""
                        }
                    ],
                    "min": "",
                    "max": ""
                },
                "layout_6394162fdb798": {
                    "key": "layout_6394162fdb798",
                    "name": "six_column",
                    "label": "Six Column",
                    "display": "block",
                    "sub_fields": [],
                    "min": "",
                    "max": ""
                },
                "layout_6395de2bb14a2": {
                    "key": "layout_6395de2bb14a2",
                    "name": "eight_column",
                    "label": "Eight Column",
                    "display": "block",
                    "sub_fields": [],
                    "min": "",
                    "max": ""
                },
                "layout_63968edab54a3": {
                    "key": "layout_63968edab54a3",
                    "name": "nice_column",
                    "label": "Nice Column",
                    "display": "block",
                    "sub_fields": [],
                    "min": "",
                    "max": ""
                },
                "layout_6396b22bc74bd": {
                    "key": "layout_6396b22bc74bd",
                    "name": "seven_column",
                    "label": "Seven Column",
                    "display": "block",
                    "sub_fields": [],
                    "min": "",
                    "max": ""
                },
                "layout_639744cc80ecb": {
                    "key": "layout_639744cc80ecb",
                    "name": "three_column",
                    "label": "Three Column",
                    "display": "block",
                    "sub_fields": [],
                    "min": "",
                    "max": ""
                },
                "layout_63993d9900439": {
                    "key": "layout_63993d9900439",
                    "name": "one_column",
                    "label": "One Column",
                    "display": "block",
                    "sub_fields": [],
                    "min": "",
                    "max": ""
                },
                "layout_63999136a3f94": {
                    "key": "layout_63999136a3f94",
                    "name": "footer_column",
                    "label": "Footer Column",
                    "display": "block",
                    "sub_fields": [],
                    "min": "",
                    "max": ""
                },
                "layout_63a45a40ab2cc": {
                    "key": "layout_63a45a40ab2cc",
                    "name": "banner_home",
                    "label": "Banner Home",
                    "display": "block",
                    "sub_fields": [
                        {
                            "key": "field_63a45af64df2a",
                            "label": "Content",
                            "name": "content",
                            "type": "wysiwyg",
                            "instructions": "",
                            "required": 0,
                            "conditional_logic": 0,
                            "wrapper": {
                                "width": "",
                                "class": "",
                                "id": ""
                            },
                            "tabs": "all",
                            "toolbar": "full",
                            "media_upload": 1,
                            "default_value": "",
                            "delay": 0
                        },
                        {
                            "key": "field_63a45f904df2b",
                            "label": "Image 1",
                            "name": "image_1",
                            "type": "image",
                            "instructions": "",
                            "required": 0,
                            "conditional_logic": 0,
                            "wrapper": {
                                "width": "",
                                "class": "",
                                "id": ""
                            },
                            "return_format": "array",
                            "preview_size": "medium",
                            "library": "all",
                            "min_width": "",
                            "min_height": "",
                            "min_size": "",
                            "max_width": "",
                            "max_height": "",
                            "max_size": "",
                            "mime_types": ""
                        }
                    ],
                    "min": "",
                    "max": ""
                },
                "layout_63a46a194f4d3": {
                    "key": "layout_63a46a194f4d3",
                    "name": "content_center",
                    "label": "Content Center",
                    "display": "block",
                    "sub_fields": [
                        {
                            "key": "field_63a46a6128535",
                            "label": "Content",
                            "name": "content",
                            "type": "wysiwyg",
                            "instructions": "",
                            "required": 0,
                            "conditional_logic": 0,
                            "wrapper": {
                                "width": "",
                                "class": "",
                                "id": ""
                            },
                            "default_value": "",
                            "tabs": "all",
                            "toolbar": "full",
                            "media_upload": 1,
                            "delay": 0
                        }
                    ],
                    "min": "",
                    "max": ""
                },
                "layout_63a46fe51cdd7": {
                    "key": "layout_63a46fe51cdd7",
                    "name": "multi_column",
                    "label": "Multi Column",
                    "display": "block",
                    "sub_fields": [
                        {
                            "key": "field_63a4703ed801d",
                            "label": "Content",
                            "name": "content",
                            "type": "repeater",
                            "instructions": "",
                            "required": 0,
                            "conditional_logic": 0,
                            "wrapper": {
                                "width": "",
                                "class": "",
                                "id": ""
                            },
                            "collapsed": "",
                            "min": 0,
                            "max": 0,
                            "layout": "table",
                            "button_label": "",
                            "sub_fields": [
                                {
                                    "key": "field_63a472fad801e",
                                    "label": "Icon",
                                    "name": "icon",
                                    "type": "image",
                                    "instructions": "",
                                    "required": 0,
                                    "conditional_logic": 0,
                                    "wrapper": {
                                        "width": "",
                                        "class": "",
                                        "id": ""
                                    },
                                    "return_format": "array",
                                    "preview_size": "medium",
                                    "library": "all",
                                    "min_width": "",
                                    "min_height": "",
                                    "min_size": "",
                                    "max_width": "",
                                    "max_height": "",
                                    "max_size": "",
                                    "mime_types": ""
                                },
                                {
                                    "key": "field_63a4732bd801f",
                                    "label": "Content",
                                    "name": "content",
                                    "type": "wysiwyg",
                                    "instructions": "",
                                    "required": 0,
                                    "conditional_logic": 0,
                                    "wrapper": {
                                        "width": "",
                                        "class": "",
                                        "id": ""
                                    },
                                    "default_value": "",
                                    "tabs": "all",
                                    "toolbar": "full",
                                    "media_upload": 1,
                                    "delay": 0
                                },
                                {
                                    "key": "field_63a47342d8020",
                                    "label": "Link",
                                    "name": "link",
                                    "type": "link",
                                    "instructions": "",
                                    "required": 0,
                                    "conditional_logic": 0,
                                    "wrapper": {
                                        "width": "",
                                        "class": "",
                                        "id": ""
                                    },
                                    "return_format": "array"
                                }
                            ]
                        }
                    ],
                    "min": "",
                    "max": ""
                }
            },
            "button_label": "Add Module",
            "min": "",
            "max": ""
        }
    ],
    "location": [
        [
            {
                "param": "post_type",
                "operator": "==",
                "value": "page"
            }
        ]
    ],
    "menu_order": 0,
    "position": "normal",
    "style": "default",
    "label_placement": "top",
    "instruction_placement": "label",
    "hide_on_screen": "",
    "active": true,
    "description": "",
    "show_in_rest": 0,
    "modified": 1671723096
}